mcp_server_multi_fetch/__init__.py
mcp_server_multi_fetch/__main__.py
mcp_server_multi_fetch/server.py
mcp_server_multi_fetch-0.8.1.dist-info/METADATA
mcp_server_multi_fetch-0.8.1.dist-info/WHEEL
mcp_server_multi_fetch-0.8.1.dist-info/entry_points.txt
mcp_server_multi_fetch-0.8.1.dist-info/licenses/LICENSE
mcp_server_multi_fetch-0.8.1.dist-info/RECORD
